network_flow_solver/.gitignore
network_flow_solver/__init__.py
network_flow_solver/main.py
network_flow_solver/main_test.py
network_flow_solver/.pytest_cache/.gitignore
network_flow_solver/.pytest_cache/CACHEDIR.TAG
network_flow_solver/.pytest_cache/README.md
network_flow_solver/.pytest_cache/v/cache/lastfailed
network_flow_solver/.pytest_cache/v/cache/nodeids
network_flow_solver/.pytest_cache/v/cache/stepwise
network_flow_solver/images/Presentation1.pptx
network_flow_solver/images/img_01.png
network_flow_solver/images/img_02.png
network_flow_solver/images/img_03.png
network_flow_solver/images/img_04.png
network_flow_solver/images/img_05.png
network_flow_solver/images/img_06.png
network_flow_solver/images/img_07.png
network_flow_solver/images/img_08.png
network_flow_solver/images/img_09.png
network_flow_solver/images/~$Presentation1.pptx
network_flow_solver-0.0.4.dist-info/METADATA
network_flow_solver-0.0.4.dist-info/WHEEL
network_flow_solver-0.0.4.dist-info/licenses/LICENSE.txt
network_flow_solver-0.0.4.dist-info/RECORD
